tinLogging/__init__.py
tinLogging/logging.py
tinLogging-0.0.3.dist-info/METADATA
tinLogging-0.0.3.dist-info/WHEEL
tinLogging-0.0.3.dist-info/top_level.txt
tinLogging-0.0.3.dist-info/RECORD
