Metadata-Version: 2.1
Name: tinLogging
Version: 0.0.3
Summary: Python library for convenient and beautiful logging of information
Home-page: https://github.com/Tinokil/tinLogging/
Author: tinokil
Author-email: zemedeuk@gmail.com
License: MIT
Project-URL: Source Code, https://github.com/Tinokil/tinLogging/blob/main/tinLogging/logging.py
Keywords: Logging,tinLogging,Logger,tinLogger,python logging
Classifier: Development Status :: 3 - Alpha
Classifier: Intended Audience :: Developers
Classifier: Programming Language :: Python :: 3.12
Classifier: License :: OSI Approved :: MIT License
Classifier: Operating System :: OS Independent
Requires-Python: >=3.6
